{"id":"4pLwGBUz89tCKppBaAlDC","title":"Books","desc":"","updated":1618941991616,"created":1617949743114,"custom":{},"fname":"readlist.books","type":"note","vault":{"fsPath":"vault"},"contentHash":"f61acc8b1d14139c23017cef638d6ceb","links":[],"anchors":{"latours-prod":{"type":"header","text":"Latour's prod","value":"latours-prod","line":8,"column":0,"depth":1},"check-in-biblioteca-itinerante-de-tramonte":{"type":"header","text":"Check in Biblioteca Itinerante de Tramonte","value":"check-in-biblioteca-itinerante-de-tramonte","line":14,"column":0,"depth":1},"long-term-preservation-of-digital-documents":{"type":"header","text":"Long-Term Preservation of Digital Documents","value":"long-term-preservation-of-digital-documents","line":20,"column":0,"depth":1}},"children":[],"parent":"iRR8MxJPGIvfKl5pcOirA","data":{}}
