{"id":"cuLAMJQqsH7IsJ1GeufGD","title":"Questions","desc":"","updated":1630301929310,"created":1609679240125,"custom":{},"fname":"dendron.questions","type":"note","vault":{"fsPath":"vault"},"contentHash":"1613fbbb154af5d6331130e01d590ca7","links":[],"anchors":{"dendron-export-markdown-preview-note-to-html-and-share":{"type":"header","text":"dendron export markdown preview note to html and share","value":"dendron-export-markdown-preview-note-to-html-and-share","line":8,"column":0,"depth":1},"dendron-snippets-definition":{"type":"header","text":"dendron snippets definition","value":"dendron-snippets-definition","line":16,"column":0,"depth":1},"dendron-copy-notes-across-vaults":{"type":"header","text":"dendron copy notes across vaults","value":"dendron-copy-notes-across-vaults","line":22,"column":0,"depth":1}},"children":[],"parent":"rInb8zzM4kEHelz4CeWDa","data":{}}
